[{
  "COMBAT_DATA":{
    "COMBAT_MODELS":[
      {
        "id":"default_combat_model",
        "data":{
            "options":{
          },
          "control_map":[
          ],
          "feedback_map":[
            {"param":"dynamic",     "key":"combatState",    "property":"state", "stateid":"combat_state",          "factor":1},
            {"param":"dynamic",     "key":"maxHealth",      "property":"state", "stateid":"health_max_state",      "factor":1},
            {"param":"dynamic",     "key":"maxArmor",       "property":"state", "stateid":"armor_max_state",       "factor":1},
            {"param":"dynamic",     "key":"health",         "property":"state", "stateid":"health_state",          "factor":1},
            {"param":"dynamic",     "key":"armor",          "property":"state", "stateid":"armor_state",           "factor":1}
          ],
          "state_map":[

          ]
        }
      }
    ]
  }
}]